aihandler/__init__.py
aihandler/base_runner.py
aihandler/controlnet_utils.py
aihandler/database.py
aihandler/extension.py
aihandler/llmrunner.py
aihandler/logger.py
aihandler/offline_client.py
aihandler/prompt_parser.py
aihandler/prompt_variable.py
aihandler/prompt_weight_bridge.py
aihandler/pyqt_offline_client.py
aihandler/qtvar.py
aihandler/runner.py
aihandler/settings.py
aihandler/settings_manager.py
aihandler/socket_server.py
aihandler/util.py
aihandler/mixins/__init__.py
aihandler/mixins/compel_mixin.py
aihandler/mixins/embedding_mixin.py
aihandler/mixins/extensions_mixin.py
aihandler/mixins/kandinsky_mixin.py
aihandler/mixins/lora_mixin.py
aihandler/mixins/memory_efficient_mixin.py
aihandler/mixins/merge_mixin.py
aihandler/mixins/scheduler_mixin.py
aihandler/mixins/txttovideo_mixin.py
aihandler-1.19.0.dist-info/LICENSE
aihandler-1.19.0.dist-info/METADATA
aihandler-1.19.0.dist-info/WHEEL
aihandler-1.19.0.dist-info/top_level.txt
aihandler-1.19.0.dist-info/RECORD
