Metadata-Version: 2.1
Name: aihandler
Version: 1.19.0
Summary: AI Handler: An engine which wraps certain huggingface models
Home-page: https://github.com/Capsize-Games/aihandler
Author: Capsize LLC
Author-email: contact@capsize.gg
License: AGPL-3.0
Keywords: ai,chatbot,chat,ai
License-File: LICENSE
Requires-Dist: einops (==0.6.0)
Requires-Dist: ninja (==1.11.1)
Requires-Dist: JIT (==0.2.7)
Requires-Dist: tqdm (==4.65.0)
Requires-Dist: omegaconf (==2.3.0)
Requires-Dist: accelerate (==0.20.3)
Requires-Dist: controlnet-aux (==0.0.6)
Requires-Dist: huggingface-hub (==0.16.3)
Requires-Dist: numpy (==1.23.5)
Requires-Dist: Pillow (==9.5.0)
Requires-Dist: pip (==23.1.2)
Requires-Dist: PyQt6 (==6.4.2)
Requires-Dist: PyQt6-Qt6 (==6.4.3)
Requires-Dist: PyQt6-sip (==13.4.1)
Requires-Dist: pyqtdarktheme (==2.1.0)
Requires-Dist: pyre-extensions (==0.0.29)
Requires-Dist: lightning (==2.0.2)
Requires-Dist: requests (==2.31.0)
Requires-Dist: requests-oauthlib (==1.3.1)
Requires-Dist: safetensors (==0.3.1)
Requires-Dist: scipy (==1.10.1)
Requires-Dist: tensorflow (==2.12.0)
Requires-Dist: tokenizers (==0.13.3)
Requires-Dist: charset-normalizer (==3.1.0)
Requires-Dist: opencv-python (==4.8.0.74)
Requires-Dist: setuptools (==67.7.2)
Requires-Dist: typing-extensions (==4.5.0)
Requires-Dist: urllib3 (==1.26.15)
Requires-Dist: diffusers (==0.18.2)
Requires-Dist: transformers (==4.30.1)
Requires-Dist: compel (==1.2.1)
Requires-Dist: sympy (==1.12.0)
Requires-Dist: regex
Requires-Dist: matplotlib (==3.7.2)
Requires-Dist: invisible-watermark (==0.2.0)
